vector_recsys_lite/__init__.py
vector_recsys_lite/algo.py
vector_recsys_lite/benchmark.py
vector_recsys_lite/cli.py
vector_recsys_lite/explain.py
vector_recsys_lite/io.py
vector_recsys_lite/tools.py
vector_recsys_lite/utils.py
vector_recsys_lite-0.1.8.dist-info/METADATA
vector_recsys_lite-0.1.8.dist-info/WHEEL
vector_recsys_lite-0.1.8.dist-info/entry_points.txt
vector_recsys_lite-0.1.8.dist-info/RECORD
