Metadata-Version: 2.3
Name: vector_recsys_lite
Version: 0.1.8
Summary: 🔥 Lightweight recommender for teaching and small-scale production
License: MIT
Keywords: recommender-system,svd,numpy,machine-learning,collaborative-filtering,education
Author: Simbarashe Timire
Author-email: stimire92@gmail.com
Requires-Python: >=3.9,<3.14
Classifier: Development Status :: 4 - Beta
Classifier: Intended Audience :: Developers
Classifier: Intended Audience :: Science/Research
Classifier: License :: OSI Approved :: MIT License
Classifier: Operating System :: OS Independent
Classifier: Programming Language :: Python :: 3
Classifier: Programming Language :: Python :: 3.9
Classifier: Programming Language :: Python :: 3.10
Classifier: Programming Language :: Python :: 3.11
Classifier: Programming Language :: Python :: 3.12
Classifier: Programming Language :: Python :: 3.13
Classifier: Topic :: Scientific/Engineering :: Information Analysis
Provides-Extra: all
Provides-Extra: hdf5
Provides-Extra: parquet
Provides-Extra: sqlite
Requires-Dist: h5py (>=3.7.0) ; extra == "hdf5" or extra == "all"
Requires-Dist: joblib (>=1.1.0)
Requires-Dist: numba (>=0.56.0) ; extra == "all"
Requires-Dist: numpy (>=1.21.0)
Requires-Dist: pandas (>=1.3.0) ; extra == "all"
Requires-Dist: pyarrow (>=7.0.0) ; extra == "parquet" or extra == "all"
Requires-Dist: rich (>=13.0.0)
Requires-Dist: scipy (>=1.7.0)
Requires-Dist: sqlalchemy (>=1.4.0) ; extra == "sqlite" or extra == "all"
Requires-Dist: typer (>=0.9.0)
